faker_nonprofit/__init__.py
faker_nonprofit/tests/__init__.py
faker_nonprofit/tests/test_fake_nonprofit.py
faker_nonprofit-1.0.0.dist-info/LICENSE
faker_nonprofit-1.0.0.dist-info/METADATA
faker_nonprofit-1.0.0.dist-info/WHEEL
faker_nonprofit-1.0.0.dist-info/top_level.txt
faker_nonprofit-1.0.0.dist-info/RECORD
