Metadata-Version: 2.1
Name: faker-nonprofit
Version: 1.0.0
Summary: Provider for Faker which adds fake nonprofit information.
Home-page: https://github.com/SFDO-Community-Sprints/Snowfakery-Nonprofit
Author: Aaron Crosman, Allison Letts, Paul Prescod
Author-email: DatagenToolkitTeam@example.invalid
License: UNKNOWN
Platform: UNKNOWN
Classifier: Programming Language :: Python :: 3.8
Classifier: Programming Language :: Python :: 3.9
Classifier: Programming Language :: Python :: 3.10
Classifier: License :: OSI Approved :: BSD License
Classifier: Operating System :: OS Independent
License-File: LICENSE
Requires-Dist: faker
